Classfile /F:/testJvm/org/fenixsoft/polymorphic/DynamicDispatch.class
  Last modified 2017-8-11; size 622 bytes
  MD5 checksum 750a788fb0686c47527dd00a7126a4b7
  Compiled from "DynamicDispatch.java"
public class org.fenixsoft.polymorphic.DynamicDispatch
  SourceFile: "DynamicDispatch.java"
  InnerClasses:
       static #9= #4 of #7; //Woman=class org/fenixsoft/polymorphic/DynamicDispatch$Woman of class org/fenixsoft/polymorphic/DynamicDispatch
       static #11= #2 of #7; //Man=class org/fenixsoft/polymorphic/DynamicDispatch$Man of class org/fenixsoft/polymorphic/DynamicDispatch
       static abstract #13= #12 of #7; //Human=class org/fenixsoft/polymorphic/DynamicDispatch$Human of class org/fenixsoft/polymorphic/DynamicDispatch
  minor version: 0
  major version: 51
  flags: ACC_PUBLIC, ACC_SUPER
Constant pool:
   #1 = Methodref          #8.#22         //  java/lang/Object."<init>":()V
   #2 = Class              #23            //  org/fenixsoft/polymorphic/DynamicDispatch$Man
   #3 = Methodref          #2.#22         //  org/fenixsoft/polymorphic/DynamicDispatch$Man."<init>":()V
   #4 = Class              #24            //  org/fenixsoft/polymorphic/DynamicDispatch$Woman
   #5 = Methodref          #4.#22         //  org/fenixsoft/polymorphic/DynamicDispatch$Woman."<init>":()V
   #6 = Methodref          #12.#25        //  org/fenixsoft/polymorphic/DynamicDispatch$Human.sayHello:()V
   #7 = Class              #26            //  org/fenixsoft/polymorphic/DynamicDispatch
   #8 = Class              #27            //  java/lang/Object
   #9 = Utf8               Woman
  #10 = Utf8               InnerClasses
  #11 = Utf8               Man
  #12 = Class              #28            //  org/fenixsoft/polymorphic/DynamicDispatch$Human
  #13 = Utf8               Human
  #14 = Utf8               <init>
  #15 = Utf8               ()V
  #16 = Utf8               Code
  #17 = Utf8               LineNumberTable
  #18 = Utf8               main
  #19 = Utf8               ([Ljava/lang/String;)V
  #20 = Utf8               SourceFile
  #21 = Utf8               DynamicDispatch.java
  #22 = NameAndType        #14:#15        //  "<init>":()V
  #23 = Utf8               org/fenixsoft/polymorphic/DynamicDispatch$Man
  #24 = Utf8               org/fenixsoft/polymorphic/DynamicDispatch$Woman
  #25 = NameAndType        #29:#15        //  sayHello:()V
  #26 = Utf8               org/fenixsoft/polymorphic/DynamicDispatch
  #27 = Utf8               java/lang/Object
  #28 = Utf8               org/fenixsoft/polymorphic/DynamicDispatch$Human
  #29 = Utf8               sayHello
{
  public org.fenixsoft.polymorphic.DynamicDispatch();
    flags: ACC_PUBLIC
    Code:
      stack=1, locals=1, args_size=1
         0: aload_0       
         1: invokespecial #1                  // Method java/lang/Object."<init>":()V
         4: return        
      LineNumberTable:
        line 7: 0
        line 18: 4

  public static void main(java.lang.String[]);
    flags: ACC_PUBLIC, ACC_STATIC
    Code:
      stack=2, locals=3, args_size=1
         0: new           #2                  // class org/fenixsoft/polymorphic/DynamicDispatch$Man
         3: dup           
         4: invokespecial #3                  // Method org/fenixsoft/polymorphic/DynamicDispatch$Man."<init>":()V
         7: astore_1      
         8: new           #4                  // class org/fenixsoft/polymorphic/DynamicDispatch$Woman
        11: dup           
        12: invokespecial #5                  // Method org/fenixsoft/polymorphic/DynamicDispatch$Woman."<init>":()V
        15: astore_2      
        16: aload_1       
        17: invokevirtual #6                  // Method org/fenixsoft/polymorphic/DynamicDispatch$Human.sayHello:()V
        20: aload_2       
        21: invokevirtual #6                  // Method org/fenixsoft/polymorphic/DynamicDispatch$Human.sayHello:()V
        24: new           #4                  // class org/fenixsoft/polymorphic/DynamicDispatch$Woman
        27: dup           
        28: invokespecial #5                  // Method org/fenixsoft/polymorphic/DynamicDispatch$Woman."<init>":()V
        31: astore_1      
        32: aload_1       
        33: invokevirtual #6                  // Method org/fenixsoft/polymorphic/DynamicDispatch$Human.sayHello:()V
        36: return        
      LineNumberTable:
        line 27: 0
        line 28: 8
        line 29: 16
        line 30: 20
        line 32: 24
        line 33: 32
        line 34: 36
}
