Classfile /F:/testJvm/com/nupt/test/TestStringPool.class
  Last modified 2017-9-9; size 653 bytes
  MD5 checksum 80d5058431d87155ee77a4a3efe4c232
  Compiled from "TestStringPool.java"
public class org.fenixsoft.clazz.TestStringPool
  SourceFile: "TestStringPool.java"
  minor version: 0
  major version: 51
  flags: ACC_PUBLIC, ACC_SUPER
Constant pool:
   #1 = Methodref          #12.#21        //  java/lang/Object."<init>":()V
   #2 = Class              #22            //  java/lang/StringBuilder
   #3 = Methodref          #2.#21         //  java/lang/StringBuilder."<init>":()V
   #4 = String             #23            //  abc
   #5 = Methodref          #2.#24         //  java/lang/StringBuilder.append:(Ljava/lang/String;)Ljava/lang/StringBuilder;
   #6 = Class              #25            //  java/lang/String
   #7 = Methodref          #6.#26         //  java/lang/String."<init>":(Ljava/lang/String;)V
   #8 = Methodref          #2.#27         //  java/lang/StringBuilder.toString:()Ljava/lang/String;
   #9 = Fieldref           #28.#29        //  java/lang/System.out:Ljava/io/PrintStream;
  #10 = Methodref          #30.#31        //  java/io/PrintStream.println:(Ljava/lang/String;)V
  #11 = Class              #32            //  org/fenixsoft/clazz/TestStringPool
  #12 = Class              #33            //  java/lang/Object
  #13 = Utf8               <init>
  #14 = Utf8               ()V
  #15 = Utf8               Code
  #16 = Utf8               LineNumberTable
  #17 = Utf8               main
  #18 = Utf8               ([Ljava/lang/String;)V
  #19 = Utf8               SourceFile
  #20 = Utf8               TestStringPool.java
  #21 = NameAndType        #13:#14        //  "<init>":()V
  #22 = Utf8               java/lang/StringBuilder
  #23 = Utf8               abc
  #24 = NameAndType        #34:#35        //  append:(Ljava/lang/String;)Ljava/lang/StringBuilder;
  #25 = Utf8               java/lang/String
  #26 = NameAndType        #13:#36        //  "<init>":(Ljava/lang/String;)V
  #27 = NameAndType        #37:#38        //  toString:()Ljava/lang/String;
  #28 = Class              #39            //  java/lang/System
  #29 = NameAndType        #40:#41        //  out:Ljava/io/PrintStream;
  #30 = Class              #42            //  java/io/PrintStream
  #31 = NameAndType        #43:#36        //  println:(Ljava/lang/String;)V
  #32 = Utf8               org/fenixsoft/clazz/TestStringPool
  #33 = Utf8               java/lang/Object
  #34 = Utf8               append
  #35 = Utf8               (Ljava/lang/String;)Ljava/lang/StringBuilder;
  #36 = Utf8               (Ljava/lang/String;)V
  #37 = Utf8               toString
  #38 = Utf8               ()Ljava/lang/String;
  #39 = Utf8               java/lang/System
  #40 = Utf8               out
  #41 = Utf8               Ljava/io/PrintStream;
  #42 = Utf8               java/io/PrintStream
  #43 = Utf8               println
{
  public org.fenixsoft.clazz.TestStringPool();
    flags: ACC_PUBLIC
    Code:
      stack=1, locals=1, args_size=1
         0: aload_0       
         1: invokespecial #1                  // Method java/lang/Object."<init>":()V
         4: return        
      LineNumberTable:
        line 3: 0

  public static void main(java.lang.String[]);
    flags: ACC_PUBLIC, ACC_STATIC
    Code:
      stack=4, locals=2, args_size=1
         0: new           #2                  // class java/lang/StringBuilder
         3: dup           
         4: invokespecial #3                  // Method java/lang/StringBuilder."<init>":()V
         7: ldc           #4                  // String abc
         9: invokevirtual #5                  // Method java/lang/StringBuilder.append:(Ljava/lang/String;)Ljava/lang/StringBuilder;
        12: new           #6                  // class java/lang/String
        15: dup           
        16: ldc           #4                  // String abc
        18: invokespecial #7                  // Method java/lang/String."<init>":(Ljava/lang/String;)V
        21: invokevirtual #5                  // Method java/lang/StringBuilder.append:(Ljava/lang/String;)Ljava/lang/StringBuilder;
        24: invokevirtual #8                  // Method java/lang/StringBuilder.toString:()Ljava/lang/String;
        27: astore_1      
        28: getstatic     #9                  // Field java/lang/System.out:Ljava/io/PrintStream;
        31: aload_1       
        32: invokevirtual #10                 // Method java/io/PrintStream.println:(Ljava/lang/String;)V
        35: return        
      LineNumberTable:
        line 6: 0
        line 7: 28
        line 8: 35
}
